slotted/__init__.py
slotted/_abc.py
slotted/_slotted.py
slotted/py.typed
slotted-5.1.0.dist-info/LICENSE
slotted-5.1.0.dist-info/METADATA
slotted-5.1.0.dist-info/WHEEL
slotted-5.1.0.dist-info/top_level.txt
slotted-5.1.0.dist-info/RECORD
